nuttcp_parser
